cartographer/__init__.py
cartographer/__version__.py
cartographer/configuration.py
cartographer/interfaces.py
cartographer/printer_interface.py
cartographer/stream.py
cartographer/klipper/__init__.py
cartographer/klipper/axis_twist_compensation.py
cartographer/klipper/bed_mesh.py
cartographer/klipper/configuration.py
cartographer/klipper/endstop.py
cartographer/klipper/extra.py
cartographer/klipper/homing.py
cartographer/klipper/logging.py
cartographer/klipper/printer.py
cartographer/klipper/probe.py
cartographer/klipper/task_executor.py
cartographer/klipper/temperature.py
cartographer/klipper/utils.py
cartographer/klipper/mcu/__init__.py
cartographer/klipper/mcu/commands.py
cartographer/klipper/mcu/constants.py
cartographer/klipper/mcu/mcu.py
cartographer/klipper/mcu/stream.py
cartographer/lib/alpha_beta_filter.py
cartographer/lib/nearest_neighbor.py
cartographer/lib/statistics.py
cartographer/macros/__init__.py
cartographer/macros/axis_twist_compensation.py
cartographer/macros/bed_mesh.py
cartographer/macros/probe.py
cartographer/macros/scan.py
cartographer/macros/touch.py
cartographer/macros/utils.py
cartographer/probe/__init__.py
cartographer/probe/probe.py
cartographer/probe/scan_mode.py
cartographer/probe/scan_model.py
cartographer/probe/touch_mode.py
jomik_cartographer-0.0.18.dist-info/METADATA
jomik_cartographer-0.0.18.dist-info/WHEEL
jomik_cartographer-0.0.18.dist-info/licenses/LICENSE
jomik_cartographer-0.0.18.dist-info/extra_metadata/release_info
jomik_cartographer-0.0.18.dist-info/RECORD
