Metadata-Version: 2.4
Name: jomik-cartographer
Version: 0.0.18
Summary: An extras for klipper to integrate with cartographer
Project-URL: homepage, https://github.com/Jomik/cartographer-klippy
Project-URL: repository, https://github.com/Jomik/cartographer-klippy
License:                     GNU GENERAL PUBLIC LICENSE
License-File: LICENSE
Keywords: 3D printing,cartographer,klipper
Classifier: Development Status :: 3 - Alpha
Classifier: Intended Audience :: End Users/Desktop
Classifier: License :: OSI Approved :: GNU General Public License v3 (GPLv3)
Requires-Python: ~=3.8
Requires-Dist: numpy<1.26,>=1.16; python_version < '3.10'
Requires-Dist: numpy~=1.16; python_version ~= '3.10'
Requires-Dist: typing-extensions~=4.12
Provides-Extra: scipy
Requires-Dist: scipy~=1.9; extra == 'scipy'
